zijinlib/__init__.py
zijinlib/file.py
zijinlib/mail.py
zijinlib/qq.py
zijinlib/spider.py
zijinlib-0.14.0.dist-info/DESCRIPTION.rst
zijinlib-0.14.0.dist-info/METADATA
zijinlib-0.14.0.dist-info/RECORD
zijinlib-0.14.0.dist-info/WHEEL
zijinlib-0.14.0.dist-info/metadata.json
zijinlib-0.14.0.dist-info/top_level.txt
