Metadata-Version: 2.0
Name: zijinlib
Version: 0.14.0
Summary: A package which can make your python programming more convenient.
Home-page: https://github.com/yuanyuanzijin/zijinlib
Author: yuanyuanzijin
Author-email: yuanyuanzijin@gmail.com
License: BSD License
